kerex/blocks/__init__.py
kerex/blocks/attention/__init__.py
kerex/blocks/attention/attention.py
kerex/blocks/attention/base_attention.py
kerex/blocks/autoencoder/__init__.py
kerex/blocks/autoencoder/base_decoder.py
kerex/blocks/autoencoder/base_encoder.py
kerex/blocks/autoencoder/decoder.py
kerex/blocks/autoencoder/encoder.py
kerex/blocks/tsmixer/__init__.py
kerex/blocks/tsmixer/tsmixer.py
kerex/callbacks/__init__.py
kerex/callbacks/callbacks.py
kerex/dataloader/__init__.py
kerex/dataloader/dataloader.py
kerex/dataloader/augmentation/__init__.py
kerex/dataloader/augmentation/random_noise.py
kerex/dataloader/augmentation/random_rotation.py
kerex/layers/__init__.py
kerex/layers/conv/__init__.py
kerex/layers/conv/base_conv.py
kerex/layers/conv/conv1d.py
kerex/layers/conv/conv2d.py
kerex/layers/conv/conv3d.py
kerex/layers/fno/__init__.py
kerex/layers/fno/base_fno.py
kerex/layers/fno/fno.py
kerex/layers/fno/spectral_conv/__init__.py
kerex/layers/fno/spectral_conv/base_spectral_conv.py
kerex/layers/fno/spectral_conv/spectral_conv.py
kerex/layers/merge/__init__.py
kerex/layers/merge/attention_gate.py
kerex/layers/pooling/__init__.py
kerex/layers/pooling/attention_pooling.py
kerex/layers/pooling/base_attention_pooling.py
kerex/layers/pooling/base_cam.py
kerex/layers/pooling/cam.py
kerex/layers/reshape/__init__.py
kerex/layers/reshape/base_fft_upsampling.py
kerex/layers/reshape/base_smooth_upsampling.py
kerex/layers/reshape/fft_upsampling.py
kerex/layers/reshape/smooth_upsampling.py
kerex/layers/wrapper/__init__.py
kerex/layers/wrapper/attention.py
kerex/layers/wrapper/cbam.py
kerex/layers/wrapper/film.py
kerex/layers/wrapper/residual.py
kerex/layers/wrapper/temporal_slice.py
kerex/layers/wrapper/weight_normalization.py
kerex/models/__init__.py
kerex/models/autoencoder/__init__.py
kerex/models/autoencoder/base_models.py
kerex/models/autoencoder/fully_convolutional_network.py
kerex/models/autoencoder/unet.py
kerex/models/neural_operator/__init__.py
kerex-1.1.5.dist-info/licenses/LICENSE
kerex-1.1.5.dist-info/METADATA
kerex-1.1.5.dist-info/WHEEL
kerex-1.1.5.dist-info/top_level.txt
kerex-1.1.5.dist-info/RECORD
